{
  "page": 406,
  "ayah_highlights": [
    {
      "page": 406,
      "line": 1,
      "sura": 46,
      "ayah": 32,
      "left": 0.08,
      "right": 0.92
    },
    {
      "page": 406,
      "line": 2,
      "sura": 46,
      "ayah": 32,
      "left": 0.3887,
      "right": 0.92
    },
    {
      "page": 406,
      "line": 2,
      "sura": 46,
      "ayah": 33,
      "left": 0.08,
      "right": 0.3887
    },
    {
      "page": 406,
      "line": 3,
      "sura": 46,
      "ayah": 33,
      "left": 0.08,
      "right": 0.92
    },
    {
      "page": 406,
      "line": 4,
      "sura": 46,
      "ayah": 33,
      "left": 0.8269,
      "right": 0.92
    },
    {
      "page": 406,
      "line": 4,
      "sura": 46,
      "ayah": 34,
      "left": 0.08,
      "right": 0.8269
    },
    {
      "page": 406,
      "line": 5,
      "sura": 46,
      "ayah": 34,
      "left": 0.08,
      "right": 0.92
    },
    {
      "page": 406,
      "line": 6,
      "sura": 46,
      "ayah": 34,
      "left": 0.7863,
      "right": 0.92
    },
    {
      "page": 406,
      "line": 6,
      "sura": 47,
      "ayah": 1,
      "left": 0.08,
      "right": 0.7863
    },
    {
      "page": 406,
      "line": 7,
      "sura": 47,
      "ayah": 1,
      "left": 0.7855,
      "right": 0.92
    },
    {
      "page": 406,
      "line": 7,
      "sura": 47,
      "ayah": 2,
      "left": 0.08,
      "right": 0.7855
    },
    {
      "page": 406,
      "line": 8,
      "sura": 47,
      "ayah": 2,
      "left": 0.3577,
      "right": 0.92
    },
    {
      "page": 406,
      "line": 8,
      "sura": 47,
      "ayah": 3,
      "left": 0.08,
      "right": 0.3577
    },
    {
      "page": 406,
      "line": 9,
      "sura": 47,
      "ayah": 3,
      "left": 0.08,
      "right": 0.92
    },
    {
      "page": 406,
      "line": 10,
      "sura": 47,
      "ayah": 3,
      "left": 0.7699,
      "right": 0.92
    },
    {
      "page": 406,
      "line": 10,
      "sura": 47,
      "ayah": 4,
      "left": 0.08,
      "right": 0.7699
    },
    {
      "page": 406,
      "line": 11,
      "sura": 47,
      "ayah": 4,
      "left": 0.1869,
      "right": 0.92
    },
    {
      "page": 406,
      "line": 11,
      "sura": 47,
      "ayah": 5,
      "left": 0.08,
      "right": 0.1869
    },
    {
      "page": 406,
      "line": 12,
      "sura": 47,
      "ayah": 5,
      "left": 0.08,
      "right": 0.92
    },
    {
      "page": 406,
      "line": 13,
      "sura": 47,
      "ayah": 5,
      "left": 0.6509,
      "right": 0.92
    },
    {
      "page": 406,
      "line": 13,
      "sura": 47,
      "ayah": 6,
      "left": 0.4051,
      "right": 0.6509
    },
    {
      "page": 406,
      "line": 13,
      "sura": 47,
      "ayah": 7,
      "left": 0.1076,
      "right": 0.4051
    },
    {
      "page": 406,
      "line": 13,
      "sura": 47,
      "ayah": 8,
      "left": 0.08,
      "right": 0.1076
    },
    {
      "page": 406,
      "line": 14,
      "sura": 47,
      "ayah": 8,
      "left": 0.2361,
      "right": 0.92
    },
    {
      "page": 406,
      "line": 14,
      "sura": 47,
      "ayah": 9,
      "left": 0.08,
      "right": 0.2361
    },
    {
      "page": 406,
      "line": 15,
      "sura": 47,
      "ayah": 9,
      "left": 0.6233,
      "right": 0.92
    },
    {
      "page": 406,
      "line": 15,
      "sura": 47,
      "ayah": 10,
      "left": 0.08,
      "right": 0.6233
    }
  ],
  "ayah_markers": [
    {
      "page": 406,
      "sura": 46,
      "ayah": 32,
      "line": 2,
      "center_x": 0.3887,
      "center_y": 0.5
    },
    {
      "page": 406,
      "sura": 46,
      "ayah": 33,
      "line": 4,
      "center_x": 0.8269,
      "center_y": 0.5
    },
    {
      "page": 406,
      "sura": 46,
      "ayah": 34,
      "line": 6,
      "center_x": 0.7863,
      "center_y": 0.5
    },
    {
      "page": 406,
      "sura": 47,
      "ayah": 1,
      "line": 7,
      "center_x": 0.7855,
      "center_y": 0.5
    },
    {
      "page": 406,
      "sura": 47,
      "ayah": 2,
      "line": 8,
      "center_x": 0.3577,
      "center_y": 0.5
    },
    {
      "page": 406,
      "sura": 47,
      "ayah": 3,
      "line": 10,
      "center_x": 0.7699,
      "center_y": 0.5
    },
    {
      "page": 406,
      "sura": 47,
      "ayah": 4,
      "line": 11,
      "center_x": 0.1869,
      "center_y": 0.5
    },
    {
      "page": 406,
      "sura": 47,
      "ayah": 5,
      "line": 13,
      "center_x": 0.6509,
      "center_y": 0.5
    },
    {
      "page": 406,
      "sura": 47,
      "ayah": 6,
      "line": 13,
      "center_x": 0.4051,
      "center_y": 0.5
    },
    {
      "page": 406,
      "sura": 47,
      "ayah": 7,
      "line": 13,
      "center_x": 0.1076,
      "center_y": 0.5
    },
    {
      "page": 406,
      "sura": 47,
      "ayah": 8,
      "line": 14,
      "center_x": 0.2361,
      "center_y": 0.5
    },
    {
      "page": 406,
      "sura": 47,
      "ayah": 9,
      "line": 15,
      "center_x": 0.6233,
      "center_y": 0.5
    },
    {
      "page": 406,
      "sura": 47,
      "ayah": 10,
      "line": 15,
      "center_x": 0.08,
      "center_y": 0.5
    }
  ],
  "sura_headers": [
    {
      "page": 406,
      "sura": 47,
      "center_x": 720,
      "center_y": 1276
    }
  ]
}