{
  "page": 270,
  "ayah_highlights": [
    {
      "page": 270,
      "line": 1,
      "sura": 22,
      "ayah": 28,
      "left": 0.03,
      "right": 0.9700000000000001,
      "confidence": 0.85,
      "source": "text_proportional"
    },
    {
      "page": 270,
      "line": 2,
      "sura": 22,
      "ayah": 28,
      "left": 0.03,
      "right": 0.9700000000000001,
      "confidence": 0.85,
      "source": "text_proportional"
    },
    {
      "page": 270,
      "line": 3,
      "sura": 22,
      "ayah": 28,
      "left": 0.2978,
      "right": 0.9700000000000001,
      "confidence": 0.95,
      "source": "visual_valley"
    },
    {
      "page": 270,
      "line": 3,
      "sura": 22,
      "ayah": 29,
      "left": 0.03,
      "right": 0.3978,
      "confidence": 0.95,
      "source": "visual_valley"
    },
    {
      "page": 270,
      "line": 4,
      "sura": 22,
      "ayah": 29,
      "left": 0.03,
      "right": 0.9700000000000001,
      "confidence": 0.85,
      "source": "text_proportional"
    },
    {
      "page": 270,
      "line": 5,
      "sura": 22,
      "ayah": 29,
      "left": 0.131,
      "right": 0.9700000000000001,
      "confidence": 0.95,
      "source": "visual_valley"
    },
    {
      "page": 270,
      "line": 5,
      "sura": 22,
      "ayah": 30,
      "left": 0.03,
      "right": 0.23099999999999998,
      "confidence": 0.95,
      "source": "visual_valley"
    },
    {
      "page": 270,
      "line": 6,
      "sura": 22,
      "ayah": 30,
      "left": 0.12150000000000001,
      "right": 0.9700000000000001,
      "confidence": 0.95,
      "source": "visual_valley"
    },
    {
      "page": 270,
      "line": 6,
      "sura": 22,
      "ayah": 31,
      "left": 0.03,
      "right": 0.22150000000000003,
      "confidence": 0.95,
      "source": "visual_valley"
    },
    {
      "page": 270,
      "line": 7,
      "sura": 22,
      "ayah": 31,
      "left": 0.1113,
      "right": 0.9700000000000001,
      "confidence": 0.95,
      "source": "visual_valley"
    },
    {
      "page": 270,
      "line": 7,
      "sura": 22,
      "ayah": 32,
      "left": 0.03,
      "right": 0.2113,
      "confidence": 0.95,
      "source": "visual_valley"
    },
    {
      "page": 270,
      "line": 8,
      "sura": 22,
      "ayah": 32,
      "left": 0.03,
      "right": 0.9700000000000001,
      "confidence": 0.85,
      "source": "text_proportional"
    },
    {
      "page": 270,
      "line": 9,
      "sura": 22,
      "ayah": 32,
      "left": 0.03,
      "right": 0.9700000000000001,
      "confidence": 0.85,
      "source": "text_proportional"
    },
    {
      "page": 270,
      "line": 10,
      "sura": 22,
      "ayah": 32,
      "left": 0.5951,
      "right": 0.9700000000000001,
      "confidence": 0.95,
      "source": "visual_valley"
    },
    {
      "page": 270,
      "line": 10,
      "sura": 22,
      "ayah": 33,
      "left": 0.03,
      "right": 0.6951,
      "confidence": 0.95,
      "source": "visual_valley"
    },
    {
      "page": 270,
      "line": 11,
      "sura": 22,
      "ayah": 33,
      "left": 0.03,
      "right": 0.9700000000000001,
      "confidence": 0.85,
      "source": "text_proportional"
    },
    {
      "page": 270,
      "line": 12,
      "sura": 22,
      "ayah": 33,
      "left": 0.5784999999999999,
      "right": 0.9700000000000001,
      "confidence": 0.95,
      "source": "visual_valley"
    },
    {
      "page": 270,
      "line": 12,
      "sura": 22,
      "ayah": 34,
      "left": 0.03,
      "right": 0.6785,
      "confidence": 0.95,
      "source": "visual_valley"
    },
    {
      "page": 270,
      "line": 13,
      "sura": 22,
      "ayah": 34,
      "left": 0.03,
      "right": 0.9700000000000001,
      "confidence": 0.85,
      "source": "text_proportional"
    },
    {
      "page": 270,
      "line": 14,
      "sura": 22,
      "ayah": 34,
      "left": 0.03,
      "right": 0.9700000000000001,
      "confidence": 0.85,
      "source": "text_proportional"
    },
    {
      "page": 270,
      "line": 15,
      "sura": 22,
      "ayah": 34,
      "left": 0.35710000000000003,
      "right": 0.9700000000000001,
      "confidence": 0.95,
      "source": "visual_valley"
    },
    {
      "page": 270,
      "line": 15,
      "sura": 22,
      "ayah": 35,
      "left": 0.03,
      "right": 0.4571,
      "confidence": 0.95,
      "source": "visual_valley"
    },
    {
      "page": 270,
      "line": 16,
      "sura": 22,
      "ayah": 35,
      "left": 0.03,
      "right": 0.9700000000000001,
      "confidence": 0.85,
      "source": "text_proportional"
    },
    {
      "page": 270,
      "line": 17,
      "sura": 22,
      "ayah": 35,
      "left": 0.03,
      "right": 0.9700000000000001,
      "confidence": 0.85,
      "source": "text_proportional"
    }
  ],
  "ayah_markers": [
    {
      "page": 270,
      "sura": 22,
      "ayah": 28,
      "line": 3,
      "center_x": 0.351,
      "center_y": 0.5
    },
    {
      "page": 270,
      "sura": 22,
      "ayah": 29,
      "line": 5,
      "center_x": 0.1843,
      "center_y": 0.5
    },
    {
      "page": 270,
      "sura": 22,
      "ayah": 30,
      "line": 6,
      "center_x": 0.2198,
      "center_y": 0.5
    },
    {
      "page": 270,
      "sura": 22,
      "ayah": 31,
      "line": 7,
      "center_x": 0.0908,
      "center_y": 0.5
    },
    {
      "page": 270,
      "sura": 22,
      "ayah": 32,
      "line": 10,
      "center_x": 0.6361,
      "center_y": 0.5
    },
    {
      "page": 270,
      "sura": 22,
      "ayah": 33,
      "line": 12,
      "center_x": 0.6705,
      "center_y": 0.5
    },
    {
      "page": 270,
      "sura": 22,
      "ayah": 34,
      "line": 15,
      "center_x": 0.3747,
      "center_y": 0.5
    },
    {
      "page": 270,
      "sura": 22,
      "ayah": 35,
      "line": 17,
      "center_x": 0.08,
      "center_y": 0.5
    }
  ],
  "sura_headers": []
}