{
  "page": 310,
  "ayah_highlights": [
    {
      "page": 310,
      "line": 1,
      "sura": 28,
      "ayah": 1,
      "left": 0.08,
      "right": 0.92
    },
    {
      "page": 310,
      "line": 2,
      "sura": 28,
      "ayah": 2,
      "left": 0.1314,
      "right": 0.92
    },
    {
      "page": 310,
      "line": 2,
      "sura": 28,
      "ayah": 3,
      "left": 0.08,
      "right": 0.1314
    },
    {
      "page": 310,
      "line": 3,
      "sura": 28,
      "ayah": 3,
      "left": 0.08,
      "right": 0.92
    },
    {
      "page": 310,
      "line": 4,
      "sura": 28,
      "ayah": 3,
      "left": 0.08,
      "right": 0.92
    },
    {
      "page": 310,
      "line": 5,
      "sura": 28,
      "ayah": 3,
      "left": 0.8857,
      "right": 0.92
    },
    {
      "page": 310,
      "line": 5,
      "sura": 28,
      "ayah": 4,
      "left": 0.08,
      "right": 0.8857
    },
    {
      "page": 310,
      "line": 6,
      "sura": 28,
      "ayah": 4,
      "left": 0.5257,
      "right": 0.92
    },
    {
      "page": 310,
      "line": 6,
      "sura": 28,
      "ayah": 5,
      "left": 0.08,
      "right": 0.5257
    },
    {
      "page": 310,
      "line": 7,
      "sura": 28,
      "ayah": 5,
      "left": 0.2343,
      "right": 0.92
    },
    {
      "page": 310,
      "line": 7,
      "sura": 28,
      "ayah": 6,
      "left": 0.08,
      "right": 0.2343
    },
    {
      "page": 310,
      "line": 8,
      "sura": 28,
      "ayah": 6,
      "left": 0.08,
      "right": 0.92
    },
    {
      "page": 310,
      "line": 9,
      "sura": 28,
      "ayah": 6,
      "left": 0.08,
      "right": 0.92
    },
    {
      "page": 310,
      "line": 10,
      "sura": 28,
      "ayah": 6,
      "left": 0.8171,
      "right": 0.92
    },
    {
      "page": 310,
      "line": 10,
      "sura": 28,
      "ayah": 7,
      "left": 0.08,
      "right": 0.8171
    },
    {
      "page": 310,
      "line": 11,
      "sura": 28,
      "ayah": 7,
      "left": 0.3714,
      "right": 0.92
    },
    {
      "page": 310,
      "line": 11,
      "sura": 28,
      "ayah": 8,
      "left": 0.08,
      "right": 0.3714
    },
    {
      "page": 310,
      "line": 12,
      "sura": 28,
      "ayah": 8,
      "left": 0.08,
      "right": 0.92
    },
    {
      "page": 310,
      "line": 13,
      "sura": 28,
      "ayah": 8,
      "left": 0.6114,
      "right": 0.92
    },
    {
      "page": 310,
      "line": 13,
      "sura": 28,
      "ayah": 9,
      "left": 0.08,
      "right": 0.6114
    },
    {
      "page": 310,
      "line": 14,
      "sura": 28,
      "ayah": 9,
      "left": 0.08,
      "right": 0.92
    },
    {
      "page": 310,
      "line": 15,
      "sura": 28,
      "ayah": 9,
      "left": 0.8686,
      "right": 0.92
    },
    {
      "page": 310,
      "line": 15,
      "sura": 28,
      "ayah": 10,
      "left": 0.08,
      "right": 0.8686
    }
  ],
  "ayah_markers": [
    {
      "page": 310,
      "sura": 28,
      "ayah": 1,
      "line": 2,
      "center_x": 0.92,
      "center_y": 0.5
    },
    {
      "page": 310,
      "sura": 28,
      "ayah": 2,
      "line": 2,
      "center_x": 0.1314,
      "center_y": 0.5
    },
    {
      "page": 310,
      "sura": 28,
      "ayah": 3,
      "line": 5,
      "center_x": 0.8857,
      "center_y": 0.5
    },
    {
      "page": 310,
      "sura": 28,
      "ayah": 4,
      "line": 6,
      "center_x": 0.5257,
      "center_y": 0.5
    },
    {
      "page": 310,
      "sura": 28,
      "ayah": 5,
      "line": 7,
      "center_x": 0.2343,
      "center_y": 0.5
    },
    {
      "page": 310,
      "sura": 28,
      "ayah": 6,
      "line": 10,
      "center_x": 0.8171,
      "center_y": 0.5
    },
    {
      "page": 310,
      "sura": 28,
      "ayah": 7,
      "line": 11,
      "center_x": 0.3714,
      "center_y": 0.5
    },
    {
      "page": 310,
      "sura": 28,
      "ayah": 8,
      "line": 13,
      "center_x": 0.6114,
      "center_y": 0.5
    },
    {
      "page": 310,
      "sura": 28,
      "ayah": 9,
      "line": 15,
      "center_x": 0.8686,
      "center_y": 0.5
    },
    {
      "page": 310,
      "sura": 28,
      "ayah": 10,
      "line": 15,
      "center_x": 0.08,
      "center_y": 0.5
    }
  ],
  "sura_headers": [
    {
      "page": 310,
      "sura": 28,
      "center_x": 720,
      "center_y": 116
    }
  ]
}